LICENSE.txt
edgar/__about__.py
edgar/__init__.py
edgar/_filings.py
edgar/_markdown.py
edgar/_party.py
edgar/attachments.py
edgar/config.py
edgar/core.py
edgar/current_filings.py
edgar/datatools.py
edgar/dates.py
edgar/earnings.py
edgar/effect.py
edgar/enums.py
edgar/filesystem.py
edgar/filtering.py
edgar/financials.py
edgar/form144.py
edgar/forms.py
edgar/headers.py
edgar/httpclient.py
edgar/httprequests.py
edgar/muniadvisors.py
edgar/paths.py
edgar/richtools.py
edgar/shelfofferings.py
edgar/storage.py
edgar/storage_management.py
edgar/urls.py
edgar/xmltools.py
edgar/abs/__init__.py
edgar/abs/abs_ee.py
edgar/abs/cmbs.py
edgar/abs/distribution.py
edgar/abs/ten_d.py
edgar/ai/__init__.py
edgar/ai/__main__.py
edgar/ai/core.py
edgar/ai/formats.py
edgar/ai/helpers.py
edgar/ai/examples/__init__.py
edgar/ai/examples/basic_usage.py
edgar/ai/exporters/__init__.py
edgar/ai/exporters/claude_desktop.py
edgar/ai/exporters/claude_skills.py
edgar/ai/mcp/__init__.py
edgar/ai/mcp/server.py
edgar/ai/mcp/docs/MCP_QUICKSTART.md
edgar/ai/mcp/tools/__init__.py
edgar/ai/mcp/tools/company_research.py
edgar/ai/mcp/tools/financial_analysis.py
edgar/ai/mcp/tools/industry_analysis.py
edgar/ai/mcp/tools/utils.py
edgar/ai/skills/__init__.py
edgar/ai/skills/base.py
edgar/ai/skills/core/SKILL.md
edgar/ai/skills/core/__init__.py
edgar/ai/skills/core/advanced-guide.md
edgar/ai/skills/core/common-questions.md
edgar/ai/skills/core/data-objects.md
edgar/ai/skills/core/form-types-reference.md
edgar/ai/skills/core/objects.md
edgar/ai/skills/core/quickstart-by-task.md
edgar/ai/skills/core/readme.md
edgar/ai/skills/core/workflows.md
edgar/bdc/__init__.py
edgar/bdc/datasets.py
edgar/bdc/investments.py
edgar/bdc/reference.py
edgar/bdc/search.py
edgar/beneficial_ownership/__init__.py
edgar/beneficial_ownership/amendments.py
edgar/beneficial_ownership/models.py
edgar/beneficial_ownership/rendering.py
edgar/beneficial_ownership/schedule13.py
edgar/company_reports/__init__.py
edgar/company_reports/_base.py
edgartools-5.13.0.dist-info/METADATA
edgartools-5.13.0.dist-info/WHEEL
edgartools-5.13.0.dist-info/entry_points.txt
edgartools-5.13.0.dist-info/licenses/LICENSE.txt
edgartools-5.13.0.dist-info/RECORD
