Metadata-Version: 2.4
Name: edgartools
Version: 5.13.0
Summary: Python library to access and analyze SEC Edgar filings, XBRL financial statements, 10-K, 10-Q, and 8-K reports
Project-URL: Homepage, https://github.com/dgunning/edgartools
Project-URL: Documentation, https://dgunning.github.io/edgartools/
Project-URL: Issues, https://github.com/dgunning/edgartools/issues
Project-URL: Source, https://github.com/dgunning/edgartools
Project-URL: Changelog, https://github.com/dgunning/edgartools/releases
Author-email: Dwight Gunning <dgunning@gmail.com>
License-Expression: MIT
License-File: LICENSE.txt
Keywords: 10-K,10-Q,13F,8-K,annual report,company filings,edgar,edgar api,edgar filings,filings,finance,financial data,financial statements,form 4,insider trading,institutional holdings,python,quarterly report,sec,sec api,sec filings,stock filings,xbrl
Classifier: Development Status :: 4 - Beta
Classifier: Intended Audience :: Developers
Classifier: Intended Audience :: Financial and Insurance Industry
Classifier: Intended Audience :: Science/Research
Classifier: License :: OSI Approved :: MIT License
Classifier: Programming Language :: Python
Classifier: Programming Language :: Python :: 3.10
Classifier: Programming Language :: Python :: 3.11
Classifier: Programming Language :: Python :: 3.12
Classifier: Programming Language :: Python :: 3.13
Classifier: Programming Language :: Python :: 3.14
Classifier: Programming Language :: Python :: Implementation :: CPython
Classifier: Programming Language :: Python :: Implementation :: PyPy
Classifier: Topic :: Office/Business :: Financial
Classifier: Topic :: Office/Business :: Financial :: Investment
Classifier: Topic :: Scientific/Engineering :: Information Analysis
Requires-Python: >=3.10
Requires-Dist: beautifulsoup4>=4.10.0
Requires-Dist: httpx>=0.25.0
Requires-Dist: httpxthrottlecache>=0.3.0
Requires-Dist: humanize>=4.0.0
Requires-Dist: jinja2>=3.1.0
Requires-Dist: lxml>=4.4
Requires-Dist: nest-asyncio>=1.5.1
Requires-Dist: orjson>=3.6.0
Requires-Dist: pandas>=2.0.0
Requires-Dist: pyarrow>=17.0.0
Requires-Dist: pydantic>=2.0.0
Requires-Dist: pyrate-limiter==3.9.0
Requires-Dist: rank-bm25>=0.2.1
Requires-Dist: rapidfuzz>=3.5.0
Requires-Dist: rich>=13.8.0
Requires-Dist: stamina>=24.2.0
Requires-Dist: tabulate>=0.9.0
Requires-Dist: textdistance>=4.5.0
Requires-Dist: tqdm>=4.62.0
Requires-Dist: unidecode>=1.2.0
Provides-Extra: ai
Requires-Dist: mcp>=1.12.3; extra == 'ai'
Requires-Dist: tiktoken>=0.10.0; extra == 'ai'
Provides-Extra: ai-dev
Requires-Dist: pytest-mock>=3.12.0; extra == 'ai-dev'
Requires-Dist: responses>=0.24.0; extra == 'ai-dev'
Provides-Extra: all-cloud
Requires-Dist: adlfs>=2023.1.0; extra == 'all-cloud'
Requires-Dist: fsspec>=2023.1.0; extra == 'all-cloud'
Requires-Dist: gcsfs>=2023.1.0; extra == 'all-cloud'
Requires-Dist: s3fs>=2023.1.0; extra == 'all-cloud'
Provides-Extra: azure
Requires-Dist: adlfs>=2023.1.0; extra == 'azure'
Requires-Dist: fsspec>=2023.1.0; extra == 'azure'
Provides-Extra: cloud
Requires-Dist: fsspec>=2023.1.0; extra == 'cloud'
Provides-Extra: data
Requires-Dist: duckdb>=1.0.0; extra == 'data'
Provides-Extra: gcs
Requires-Dist: fsspec>=2023.1.0; extra == 'gcs'
Requires-Dist: gcsfs>=2023.1.0; extra == 'gcs'
Provides-Extra: s3
Requires-Dist: fsspec>=2023.1.0; extra == 's3'
Requires-Dist: s3fs>=2023.1.0; extra == 's3'
Provides-Extra: test-harness
Requires-Dist: click>=8.0.0; extra == 'test-harness'
